emtax/__init__.py
emtax/cli.py
emtax/commands/__init__.py
emtax/commands/download.py
emtax/commands/download_abundance.py
emtax/commands/get_abundance.py
emtax/commands/get_abundance_fixed.py
emtax/commands/hpc.py
emtax/commands/hpc_impl.py
emtax/commands/status.py
emtax/templates/job_script.sh
emtax/templates/simple_job_script.sh
emtax/templates/simple_job_script_fixed.sh
emtax/utils/__init__.py
emtax/utils/config.py
emtax/utils/ssh.py
emtax/utils/workflow_updated.py
emtax-0.2.5.dist-info/licenses/LICENSE
emtax-0.2.5.dist-info/METADATA
emtax-0.2.5.dist-info/WHEEL
emtax-0.2.5.dist-info/entry_points.txt
emtax-0.2.5.dist-info/top_level.txt
emtax-0.2.5.dist-info/RECORD
