Metadata-Version: 2.4
Name: emtax
Version: 0.2.5
Summary: Bioinformatics workflow management tool for taxonomic profiling on HPC systems
Home-page: https://github.com/dhruvac29/emtax
Author: Dhruvil Chodvadiya
Author-email: Dhruvil Chodvadiya <your.email@example.com>
License: MIT
Project-URL: Homepage, https://github.com/dhruvac29/emtax
Project-URL: Bug Tracker, https://github.com/dhruvac29/emtax/issues
Keywords: bioinformatics,taxonomy,workflow,hpc
Classifier: Programming Language :: Python :: 3
Classifier: License :: OSI Approved :: MIT License
Classifier: Operating System :: OS Independent
Classifier: Topic :: Scientific/Engineering :: Bio-Informatics
Requires-Python: >=3.9
License-File: LICENSE
Requires-Dist: paramiko>=2.7.2
Requires-Dist: click>=7.1.2
Requires-Dist: pyyaml>=5.4.1
Requires-Dist: tqdm>=4.61.0
Requires-Dist: pandas>=1.3.0
Dynamic: author
Dynamic: home-page
Dynamic: license-file
Dynamic: requires-python
